[{"nama":"Kec. Pati","kode_wilayah":"031810  ","id_level_wilayah":3,"mst_kode_wilayah":"031800  ","induk_provinsi":"Prov. Jawa Tengah","kode_wilayah_induk_provinsi":"030000  ","induk_kabupaten":"Kab. Pati","kode_wilayah_induk_kabupaten":"031800  ","tk_n":1,"tk_s":54,"tk":55,"kb_n":0,"kb_s":39,"kb":39,"tpa_n":0,"tpa_s":7,"tpa":7,"sps_n":0,"sps_s":0,"sps":0,"pkbm_n":0,"pkbm_s":1,"pkbm":1,"skb_n":1,"skb_s":0,"skb":1,"sd_n":51,"sd_s":12,"sd":63,"smp_n":8,"smp_s":5,"smp":13,"sma_n":3,"sma_s":7,"sma":10,"smk_n":2,"smk_s":8,"smk":10,"slb_n":0,"slb_s":0,"slb":0,"sekolah_n":66,"sekolah_s":133,"sekolah":199},{"nama":"Kec. Juwana","kode_wilayah":"031808  ","id_level_wilayah":3,"mst_kode_wilayah":"031800  ","induk_provinsi":"Prov. Jawa Tengah","kode_wilayah_induk_provinsi":"030000  ","induk_kabupaten":"Kab. Pati","kode_wilayah_induk_kabupaten":"031800  ","tk_n":0,"tk_s":43,"tk":43,"kb_n":0,"kb_s":34,"kb":34,"tpa_n":0,"tpa_s":4,"tpa":4,"sps_n":0,"sps_s":0,"sps":0,"pkbm_n":0,"pkbm_s":1,"pkbm":1,"skb_n":0,"skb_s":0,"skb":0,"sd_n":40,"sd_s":5,"sd":45,"smp_n":4,"smp_s":3,"smp":7,"sma_n":1,"sma_s":1,"sma":2,"smk_n":0,"smk_s":3,"smk":3,"slb_n":0,"slb_s":0,"slb":0,"sekolah_n":45,"sekolah_s":94,"sekolah":139},{"nama":"Kec. Kayen","kode_wilayah":"031802  ","id_level_wilayah":3,"mst_kode_wilayah":"031800  ","induk_provinsi":"Prov. Jawa Tengah","kode_wilayah_induk_provinsi":"030000  ","induk_kabupaten":"Kab. Pati","kode_wilayah_induk_kabupaten":"031800  ","tk_n":0,"tk_s":31,"tk":31,"kb_n":0,"kb_s":29,"kb":29,"tpa_n":0,"tpa_s":2,"tpa":2,"sps_n":0,"sps_s":0,"sps":0,"pkbm_n":0,"pkbm_s":1,"pkbm":1,"skb_n":0,"skb_s":0,"skb":0,"sd_n":38,"sd_s":0,"sd":38,"smp_n":3,"smp_s":6,"smp":9,"sma_n":1,"sma_s":4,"sma":5,"smk_n":0,"smk_s":2,"smk":2,"slb_n":0,"slb_s":0,"slb":0,"sekolah_n":42,"sekolah_s":75,"sekolah":117},{"nama":"Kec. Sukolilo","kode_wilayah":"031801  ","id_level_wilayah":3,"mst_kode_wilayah":"031800  ","induk_provinsi":"Prov. Jawa Tengah","kode_wilayah_induk_provinsi":"030000  ","induk_kabupaten":"Kab. Pati","kode_wilayah_induk_kabupaten":"031800  ","tk_n":0,"tk_s":25,"tk":25,"kb_n":0,"kb_s":31,"kb":31,"tpa_n":0,"tpa_s":1,"tpa":1,"sps_n":0,"sps_s":0,"sps":0,"pkbm_n":0,"pkbm_s":1,"pkbm":1,"skb_n":0,"skb_s":0,"skb":0,"sd_n":38,"sd_s":2,"sd":40,"smp_n":5,"smp_s":3,"smp":8,"sma_n":0,"sma_s":1,"sma":1,"smk_n":0,"smk_s":2,"smk":2,"slb_n":0,"slb_s":2,"slb":2,"sekolah_n":43,"sekolah_s":68,"sekolah":111},{"nama":"Kec. Margoyoso","kode_wilayah":"031817  ","id_level_wilayah":3,"mst_kode_wilayah":"031800  ","induk_provinsi":"Prov. Jawa Tengah","kode_wilayah_induk_provinsi":"030000  ","induk_kabupaten":"Kab. Pati","kode_wilayah_induk_kabupaten":"031800  ","tk_n":0,"tk_s":32,"tk":32,"kb_n":0,"kb_s":28,"kb":28,"tpa_n":0,"tpa_s":2,"tpa":2,"sps_n":0,"sps_s":0,"sps":0,"pkbm_n":0,"pkbm_s":1,"pkbm":1,"skb_n":0,"skb_s":0,"skb":0,"sd_n":30,"sd_s":2,"sd":32,"smp_n":3,"smp_s":2,"smp":5,"sma_n":0,"sma_s":0,"sma":0,"smk_n":0,"smk_s":5,"smk":5,"slb_n":0,"slb_s":0,"slb":0,"sekolah_n":33,"sekolah_s":72,"sekolah":105},{"nama":"Kec. Tayu","kode_wilayah":"031820  ","id_level_wilayah":3,"mst_kode_wilayah":"031800  ","induk_provinsi":"Prov. Jawa Tengah","kode_wilayah_induk_provinsi":"030000  ","induk_kabupaten":"Kab. Pati","kode_wilayah_induk_kabupaten":"031800  ","tk_n":0,"tk_s":28,"tk":28,"kb_n":0,"kb_s":20,"kb":20,"tpa_n":0,"tpa_s":2,"tpa":2,"sps_n":0,"sps_s":3,"sps":3,"pkbm_n":0,"pkbm_s":1,"pkbm":1,"skb_n":0,"skb_s":0,"skb":0,"sd_n":28,"sd_s":7,"sd":35,"smp_n":2,"smp_s":4,"smp":6,"sma_n":1,"sma_s":1,"sma":2,"smk_n":0,"smk_s":5,"smk":5,"slb_n":0,"slb_s":0,"slb":0,"sekolah_n":31,"sekolah_s":71,"sekolah":102},{"nama":"Kec. Margorejo","kode_wilayah":"031812  ","id_level_wilayah":3,"mst_kode_wilayah":"031800  ","induk_provinsi":"Prov. Jawa Tengah","kode_wilayah_induk_provinsi":"030000  ","induk_kabupaten":"Kab. Pati","kode_wilayah_induk_kabupaten":"031800  ","tk_n":0,"tk_s":27,"tk":27,"kb_n":0,"kb_s":19,"kb":19,"tpa_n":0,"tpa_s":3,"tpa":3,"sps_n":0,"sps_s":0,"sps":0,"pkbm_n":0,"pkbm_s":0,"pkbm":0,"skb_n":0,"skb_s":0,"skb":0,"sd_n":29,"sd_s":3,"sd":32,"smp_n":2,"smp_s":3,"smp":5,"sma_n":0,"sma_s":2,"sma":2,"smk_n":3,"smk_s":1,"smk":4,"slb_n":1,"slb_s":1,"slb":2,"sekolah_n":35,"sekolah_s":59,"sekolah":94},{"nama":"Kec. Winong","kode_wilayah":"031804  ","id_level_wilayah":3,"mst_kode_wilayah":"031800  ","induk_provinsi":"Prov. Jawa Tengah","kode_wilayah_induk_provinsi":"030000  ","induk_kabupaten":"Kab. Pati","kode_wilayah_induk_kabupaten":"031800  ","tk_n":0,"tk_s":33,"tk":33,"kb_n":0,"kb_s":16,"kb":16,"tpa_n":0,"tpa_s":0,"tpa":0,"sps_n":0,"sps_s":0,"sps":0,"pkbm_n":0,"pkbm_s":1,"pkbm":1,"skb_n":0,"skb_s":0,"skb":0,"sd_n":40,"sd_s":0,"sd":40,"smp_n":2,"smp_s":1,"smp":3,"sma_n":0,"sma_s":0,"sma":0,"smk_n":0,"smk_s":1,"smk":1,"slb_n":0,"slb_s":0,"slb":0,"sekolah_n":42,"sekolah_s":52,"sekolah":94},{"nama":"Kec. Jakenan","kode_wilayah":"031809  ","id_level_wilayah":3,"mst_kode_wilayah":"031800  ","induk_provinsi":"Prov. Jawa Tengah","kode_wilayah_induk_provinsi":"030000  ","induk_kabupaten":"Kab. Pati","kode_wilayah_induk_kabupaten":"031800  ","tk_n":0,"tk_s":29,"tk":29,"kb_n":0,"kb_s":26,"kb":26,"tpa_n":0,"tpa_s":0,"tpa":0,"sps_n":0,"sps_s":0,"sps":0,"pkbm_n":0,"pkbm_s":1,"pkbm":1,"skb_n":0,"skb_s":0,"skb":0,"sd_n":27,"sd_s":1,"sd":28,"smp_n":2,"smp_s":1,"smp":3,"sma_n":1,"sma_s":0,"sma":1,"smk_n":0,"smk_s":1,"smk":1,"slb_n":0,"slb_s":0,"slb":0,"sekolah_n":30,"sekolah_s":59,"sekolah":89},{"nama":"Kec. Tlogowungu","kode_wilayah":"031814  ","id_level_wilayah":3,"mst_kode_wilayah":"031800  ","induk_provinsi":"Prov. Jawa Tengah","kode_wilayah_induk_provinsi":"030000  ","induk_kabupaten":"Kab. Pati","kode_wilayah_induk_kabupaten":"031800  ","tk_n":0,"tk_s":20,"tk":20,"kb_n":0,"kb_s":26,"kb":26,"tpa_n":0,"tpa_s":0,"tpa":0,"sps_n":0,"sps_s":3,"sps":3,"pkbm_n":0,"pkbm_s":1,"pkbm":1,"skb_n":0,"skb_s":0,"skb":0,"sd_n":29,"sd_s":1,"sd":30,"smp_n":2,"smp_s":1,"smp":3,"sma_n":0,"sma_s":0,"sma":0,"smk_n":0,"smk_s":1,"smk":1,"slb_n":0,"slb_s":0,"slb":0,"sekolah_n":31,"sekolah_s":53,"sekolah":84},{"nama":"Kec. Gabus","kode_wilayah":"031811  ","id_level_wilayah":3,"mst_kode_wilayah":"031800  ","induk_provinsi":"Prov. Jawa Tengah","kode_wilayah_induk_provinsi":"030000  ","induk_kabupaten":"Kab. Pati","kode_wilayah_induk_kabupaten":"031800  ","tk_n":1,"tk_s":26,"tk":27,"kb_n":0,"kb_s":12,"kb":12,"tpa_n":0,"tpa_s":2,"tpa":2,"sps_n":0,"sps_s":1,"sps":1,"pkbm_n":0,"pkbm_s":1,"pkbm":1,"skb_n":0,"skb_s":0,"skb":0,"sd_n":33,"sd_s":1,"sd":34,"smp_n":2,"smp_s":1,"smp":3,"sma_n":0,"sma_s":1,"sma":1,"smk_n":0,"smk_s":2,"smk":2,"slb_n":0,"slb_s":0,"slb":0,"sekolah_n":36,"sekolah_s":47,"sekolah":83},{"nama":"Kec. Trangkil","kode_wilayah":"031816  ","id_level_wilayah":3,"mst_kode_wilayah":"031800  ","induk_provinsi":"Prov. Jawa Tengah","kode_wilayah_induk_provinsi":"030000  ","induk_kabupaten":"Kab. Pati","kode_wilayah_induk_kabupaten":"031800  ","tk_n":0,"tk_s":17,"tk":17,"kb_n":0,"kb_s":22,"kb":22,"tpa_n":0,"tpa_s":0,"tpa":0,"sps_n":0,"sps_s":5,"sps":5,"pkbm_n":0,"pkbm_s":2,"pkbm":2,"skb_n":0,"skb_s":0,"skb":0,"sd_n":28,"sd_s":2,"sd":30,"smp_n":2,"smp_s":2,"smp":4,"sma_n":0,"sma_s":1,"sma":1,"smk_n":0,"smk_s":0,"smk":0,"slb_n":0,"slb_s":0,"slb":0,"sekolah_n":30,"sekolah_s":51,"sekolah":81},{"nama":"Kec. Pucakwangi","kode_wilayah":"031805  ","id_level_wilayah":3,"mst_kode_wilayah":"031800  ","induk_provinsi":"Prov. Jawa Tengah","kode_wilayah_induk_provinsi":"030000  ","induk_kabupaten":"Kab. Pati","kode_wilayah_induk_kabupaten":"031800  ","tk_n":0,"tk_s":25,"tk":25,"kb_n":0,"kb_s":20,"kb":20,"tpa_n":0,"tpa_s":0,"tpa":0,"sps_n":0,"sps_s":2,"sps":2,"pkbm_n":0,"pkbm_s":1,"pkbm":1,"skb_n":0,"skb_s":0,"skb":0,"sd_n":27,"sd_s":0,"sd":27,"smp_n":4,"smp_s":0,"smp":4,"sma_n":0,"sma_s":0,"sma":0,"smk_n":0,"smk_s":2,"smk":2,"slb_n":0,"slb_s":0,"slb":0,"sekolah_n":31,"sekolah_s":50,"sekolah":81},{"nama":"Kec. Tambakromo","kode_wilayah":"031803  ","id_level_wilayah":3,"mst_kode_wilayah":"031800  ","induk_provinsi":"Prov. Jawa Tengah","kode_wilayah_induk_provinsi":"030000  ","induk_kabupaten":"Kab. Pati","kode_wilayah_induk_kabupaten":"031800  ","tk_n":0,"tk_s":25,"tk":25,"kb_n":0,"kb_s":17,"kb":17,"tpa_n":0,"tpa_s":0,"tpa":0,"sps_n":0,"sps_s":1,"sps":1,"pkbm_n":0,"pkbm_s":1,"pkbm":1,"skb_n":0,"skb_s":0,"skb":0,"sd_n":32,"sd_s":0,"sd":32,"smp_n":4,"smp_s":0,"smp":4,"sma_n":0,"sma_s":0,"sma":0,"smk_n":0,"smk_s":0,"smk":0,"slb_n":0,"slb_s":0,"slb":0,"sekolah_n":36,"sekolah_s":44,"sekolah":80},{"nama":"Kec. Cluwak","kode_wilayah":"031819  ","id_level_wilayah":3,"mst_kode_wilayah":"031800  ","induk_provinsi":"Prov. Jawa Tengah","kode_wilayah_induk_provinsi":"030000  ","induk_kabupaten":"Kab. Pati","kode_wilayah_induk_kabupaten":"031800  ","tk_n":0,"tk_s":24,"tk":24,"kb_n":0,"kb_s":16,"kb":16,"tpa_n":0,"tpa_s":1,"tpa":1,"sps_n":0,"sps_s":3,"sps":3,"pkbm_n":0,"pkbm_s":1,"pkbm":1,"skb_n":0,"skb_s":0,"skb":0,"sd_n":28,"sd_s":0,"sd":28,"smp_n":1,"smp_s":1,"smp":2,"sma_n":0,"sma_s":0,"sma":0,"smk_n":1,"smk_s":0,"smk":1,"slb_n":0,"slb_s":0,"slb":0,"sekolah_n":30,"sekolah_s":46,"sekolah":76},{"nama":"Kec. Jaken","kode_wilayah":"031806  ","id_level_wilayah":3,"mst_kode_wilayah":"031800  ","induk_provinsi":"Prov. Jawa Tengah","kode_wilayah_induk_provinsi":"030000  ","induk_kabupaten":"Kab. Pati","kode_wilayah_induk_kabupaten":"031800  ","tk_n":0,"tk_s":18,"tk":18,"kb_n":0,"kb_s":27,"kb":27,"tpa_n":0,"tpa_s":0,"tpa":0,"sps_n":0,"sps_s":0,"sps":0,"pkbm_n":0,"pkbm_s":1,"pkbm":1,"skb_n":0,"skb_s":0,"skb":0,"sd_n":26,"sd_s":0,"sd":26,"smp_n":3,"smp_s":0,"smp":3,"sma_n":0,"sma_s":0,"sma":0,"smk_n":0,"smk_s":0,"smk":0,"slb_n":0,"slb_s":0,"slb":0,"sekolah_n":29,"sekolah_s":46,"sekolah":75},{"nama":"Kec. Dukuhseti","kode_wilayah":"031821  ","id_level_wilayah":3,"mst_kode_wilayah":"031800  ","induk_provinsi":"Prov. Jawa Tengah","kode_wilayah_induk_provinsi":"030000  ","induk_kabupaten":"Kab. Pati","kode_wilayah_induk_kabupaten":"031800  ","tk_n":1,"tk_s":18,"tk":19,"kb_n":0,"kb_s":17,"kb":17,"tpa_n":0,"tpa_s":0,"tpa":0,"sps_n":0,"sps_s":0,"sps":0,"pkbm_n":0,"pkbm_s":1,"pkbm":1,"skb_n":0,"skb_s":0,"skb":0,"sd_n":25,"sd_s":1,"sd":26,"smp_n":2,"smp_s":2,"smp":4,"sma_n":0,"sma_s":1,"sma":1,"smk_n":0,"smk_s":5,"smk":5,"slb_n":0,"slb_s":0,"slb":0,"sekolah_n":28,"sekolah_s":45,"sekolah":73},{"nama":"Kec. Wedarijaksa","kode_wilayah":"031815  ","id_level_wilayah":3,"mst_kode_wilayah":"031800  ","induk_provinsi":"Prov. Jawa Tengah","kode_wilayah_induk_provinsi":"030000  ","induk_kabupaten":"Kab. Pati","kode_wilayah_induk_kabupaten":"031800  ","tk_n":0,"tk_s":20,"tk":20,"kb_n":0,"kb_s":19,"kb":19,"tpa_n":0,"tpa_s":1,"tpa":1,"sps_n":0,"sps_s":0,"sps":0,"pkbm_n":0,"pkbm_s":1,"pkbm":1,"skb_n":0,"skb_s":0,"skb":0,"sd_n":27,"sd_s":0,"sd":27,"smp_n":2,"smp_s":2,"smp":4,"sma_n":0,"sma_s":1,"sma":1,"smk_n":0,"smk_s":0,"smk":0,"slb_n":0,"slb_s":0,"slb":0,"sekolah_n":29,"sekolah_s":44,"sekolah":73},{"nama":"Kec. Gembong","kode_wilayah":"031813  ","id_level_wilayah":3,"mst_kode_wilayah":"031800  ","induk_provinsi":"Prov. Jawa Tengah","kode_wilayah_induk_provinsi":"030000  ","induk_kabupaten":"Kab. Pati","kode_wilayah_induk_kabupaten":"031800  ","tk_n":0,"tk_s":18,"tk":18,"kb_n":0,"kb_s":22,"kb":22,"tpa_n":0,"tpa_s":1,"tpa":1,"sps_n":0,"sps_s":0,"sps":0,"pkbm_n":0,"pkbm_s":1,"pkbm":1,"skb_n":0,"skb_s":0,"skb":0,"sd_n":23,"sd_s":0,"sd":23,"smp_n":1,"smp_s":2,"smp":3,"sma_n":0,"sma_s":1,"sma":1,"smk_n":0,"smk_s":2,"smk":2,"slb_n":0,"slb_s":0,"slb":0,"sekolah_n":24,"sekolah_s":47,"sekolah":71},{"nama":"Kec. Batangan","kode_wilayah":"031807  ","id_level_wilayah":3,"mst_kode_wilayah":"031800  ","induk_provinsi":"Prov. Jawa Tengah","kode_wilayah_induk_provinsi":"030000  ","induk_kabupaten":"Kab. Pati","kode_wilayah_induk_kabupaten":"031800  ","tk_n":0,"tk_s":19,"tk":19,"kb_n":0,"kb_s":18,"kb":18,"tpa_n":0,"tpa_s":0,"tpa":0,"sps_n":0,"sps_s":5,"sps":5,"pkbm_n":0,"pkbm_s":1,"pkbm":1,"skb_n":0,"skb_s":0,"skb":0,"sd_n":22,"sd_s":0,"sd":22,"smp_n":2,"smp_s":0,"smp":2,"sma_n":1,"sma_s":0,"sma":1,"smk_n":0,"smk_s":1,"smk":1,"slb_n":0,"slb_s":0,"slb":0,"sekolah_n":25,"sekolah_s":44,"sekolah":69},{"nama":"Kec. Gunung Wungkal","kode_wilayah":"031818  ","id_level_wilayah":3,"mst_kode_wilayah":"031800  ","induk_provinsi":"Prov. Jawa Tengah","kode_wilayah_induk_provinsi":"030000  ","induk_kabupaten":"Kab. Pati","kode_wilayah_induk_kabupaten":"031800  ","tk_n":0,"tk_s":18,"tk":18,"kb_n":0,"kb_s":21,"kb":21,"tpa_n":0,"tpa_s":0,"tpa":0,"sps_n":0,"sps_s":0,"sps":0,"pkbm_n":0,"pkbm_s":1,"pkbm":1,"skb_n":0,"skb_s":0,"skb":0,"sd_n":21,"sd_s":0,"sd":21,"smp_n":2,"smp_s":0,"smp":2,"sma_n":0,"sma_s":0,"sma":0,"smk_n":0,"smk_s":1,"smk":1,"slb_n":0,"slb_s":0,"slb":0,"sekolah_n":23,"sekolah_s":41,"sekolah":64}]