[{"nama":"TK NEGERI TUJUH BELAS","sekolah_id":"4C3B05BF-D402-4BE1-91A3-2AA8BDBAB788","npsn":69845490,"jumlah_kirim":3,"ptk":2,"pegawai":1,"pd":8,"rombel":2,"jml_rk":2,"jml_lab":0,"jml_perpus":0,"induk_kecamatan":"Kec. Tujuh Belas","kode_wilayah_induk_kecamatan":"130817  ","induk_kabupaten":"Kab. Bengkayang","kode_wilayah_induk_kabupaten":"130800  ","induk_provinsi":"Prov. Kalimantan Barat","kode_wilayah_induk_provinsi":"130000  ","bentuk_pendidikan":"TK","status_sekolah":"Negeri","sinkron_terakhir":"26 Apr 2024 08:45:39","sekolah_id_enkrip":"4FC24C0BAB66D1305DCA                                                                                "},{"nama":"TK ARRAHMAN","sekolah_id":"D79F10C7-1FED-489D-8A64-035B551BEBE6","npsn":69896566,"jumlah_kirim":0,"ptk":2,"pegawai":1,"pd":0,"rombel":0,"jml_rk":0,"jml_lab":0,"jml_perpus":0,"induk_kecamatan":"Kec. Tujuh Belas","kode_wilayah_induk_kecamatan":"130817  ","induk_kabupaten":"Kab. Bengkayang","kode_wilayah_induk_kabupaten":"130800  ","induk_provinsi":"Prov. Kalimantan Barat","kode_wilayah_induk_provinsi":"130000  ","bentuk_pendidikan":"TK","status_sekolah":"Swasta","sinkron_terakhir":"28 Mar 2024 05:43:53","sekolah_id_enkrip":"C80F21A0ECA8798F521C                                                                                "},{"nama":"TK BUNDA TERESA","sekolah_id":"29D371FD-B1D0-412B-B55A-C4F388256B46","npsn":30108697,"jumlah_kirim":3,"ptk":3,"pegawai":1,"pd":61,"rombel":4,"jml_rk":2,"jml_lab":0,"jml_perpus":0,"induk_kecamatan":"Kec. Tujuh Belas","kode_wilayah_induk_kecamatan":"130817  ","induk_kabupaten":"Kab. Bengkayang","kode_wilayah_induk_kabupaten":"130800  ","induk_provinsi":"Prov. Kalimantan Barat","kode_wilayah_induk_provinsi":"130000  ","bentuk_pendidikan":"TK","status_sekolah":"Swasta","sinkron_terakhir":"23 Jun 2024 19:11:46","sekolah_id_enkrip":"7C2AF24572CD5D0BD5D4                                                                                "},{"nama":"TK CAHAYA KASIH","sekolah_id":"071A3479-7DA6-40EC-8CCA-831636AFEC5A","npsn":70008796,"jumlah_kirim":0,"ptk":1,"pegawai":1,"pd":0,"rombel":0,"jml_rk":0,"jml_lab":0,"jml_perpus":0,"induk_kecamatan":"Kec. Tujuh Belas","kode_wilayah_induk_kecamatan":"130817  ","induk_kabupaten":"Kab. Bengkayang","kode_wilayah_induk_kabupaten":"130800  ","induk_provinsi":"Prov. Kalimantan Barat","kode_wilayah_induk_provinsi":"130000  ","bentuk_pendidikan":"TK","status_sekolah":"Swasta","sinkron_terakhir":"24 Feb 2024 22:31:53","sekolah_id_enkrip":"75E63BEF1946C33E6CB0                                                                                "},{"nama":"TK EFATHA","sekolah_id":"D316287A-6D13-464B-B957-C043FA4C9942","npsn":30108703,"jumlah_kirim":0,"ptk":1,"pegawai":1,"pd":0,"rombel":0,"jml_rk":0,"jml_lab":0,"jml_perpus":0,"induk_kecamatan":"Kec. Tujuh Belas","kode_wilayah_induk_kecamatan":"130817  ","induk_kabupaten":"Kab. Bengkayang","kode_wilayah_induk_kabupaten":"130800  ","induk_provinsi":"Prov. Kalimantan Barat","kode_wilayah_induk_provinsi":"130000  ","bentuk_pendidikan":"TK","status_sekolah":"Swasta","sinkron_terakhir":"21 May 2024 19:30:36","sekolah_id_enkrip":"E15A96B2865628637A28                                                                                "},{"nama":"TK PELITA NUSANTARA","sekolah_id":"47321161-47FC-4451-A8FB-9829FFBFA77A","npsn":30108710,"jumlah_kirim":0,"ptk":1,"pegawai":1,"pd":0,"rombel":0,"jml_rk":0,"jml_lab":0,"jml_perpus":0,"induk_kecamatan":"Kec. Tujuh Belas","kode_wilayah_induk_kecamatan":"130817  ","induk_kabupaten":"Kab. Bengkayang","kode_wilayah_induk_kabupaten":"130800  ","induk_provinsi":"Prov. Kalimantan Barat","kode_wilayah_induk_provinsi":"130000  ","bentuk_pendidikan":"TK","status_sekolah":"Swasta","sinkron_terakhir":"27 Jun 2024 05:37:24","sekolah_id_enkrip":"A9FFAAAD82BA3EDAB841                                                                                "},{"nama":"TK RAUDHATUL JANNAH","sekolah_id":"F513AE7A-EDAD-4EC7-B5FB-EF04C98CE004","npsn":30108713,"jumlah_kirim":0,"ptk":2,"pegawai":1,"pd":0,"rombel":0,"jml_rk":0,"jml_lab":0,"jml_perpus":0,"induk_kecamatan":"Kec. Tujuh Belas","kode_wilayah_induk_kecamatan":"130817  ","induk_kabupaten":"Kab. Bengkayang","kode_wilayah_induk_kabupaten":"130800  ","induk_provinsi":"Prov. Kalimantan Barat","kode_wilayah_induk_provinsi":"130000  ","bentuk_pendidikan":"TK","status_sekolah":"Swasta","sinkron_terakhir":"29 Feb 2024 21:04:01","sekolah_id_enkrip":"D30A1ECEDBF4AB3A9A89                                                                                "},{"nama":"TK SUMBER ILMU ","sekolah_id":"7160B407-542B-4C9E-B033-6D379E13D662","npsn":69943461,"jumlah_kirim":0,"ptk":1,"pegawai":1,"pd":0,"rombel":0,"jml_rk":0,"jml_lab":0,"jml_perpus":0,"induk_kecamatan":"Kec. Tujuh Belas","kode_wilayah_induk_kecamatan":"130817  ","induk_kabupaten":"Kab. Bengkayang","kode_wilayah_induk_kabupaten":"130800  ","induk_provinsi":"Prov. Kalimantan Barat","kode_wilayah_induk_provinsi":"130000  ","bentuk_pendidikan":"TK","status_sekolah":"Swasta","sinkron_terakhir":"13 Feb 2024 15:47:01","sekolah_id_enkrip":"614C9C74A4FB0FF7E401                                                                                "},{"nama":"KB ADUB BASAMU","sekolah_id":"03E7BDFB-6592-403C-863B-02E280404878","npsn":70003250,"jumlah_kirim":0,"ptk":2,"pegawai":1,"pd":0,"rombel":0,"jml_rk":0,"jml_lab":0,"jml_perpus":0,"induk_kecamatan":"Kec. Tujuh Belas","kode_wilayah_induk_kecamatan":"130817  ","induk_kabupaten":"Kab. Bengkayang","kode_wilayah_induk_kabupaten":"130800  ","induk_provinsi":"Prov. Kalimantan Barat","kode_wilayah_induk_provinsi":"130000  ","bentuk_pendidikan":"KB","status_sekolah":"Swasta","sinkron_terakhir":"21 Feb 2024 20:19:59","sekolah_id_enkrip":"700EA660BA4AB916A373                                                                                "},{"nama":"KB MASA DEPAN CERAH","sekolah_id":"19C1781C-E0FD-4D85-B230-194635AF3240","npsn":69845524,"jumlah_kirim":0,"ptk":2,"pegawai":3,"pd":0,"rombel":0,"jml_rk":0,"jml_lab":0,"jml_perpus":0,"induk_kecamatan":"Kec. Tujuh Belas","kode_wilayah_induk_kecamatan":"130817  ","induk_kabupaten":"Kab. Bengkayang","kode_wilayah_induk_kabupaten":"130800  ","induk_provinsi":"Prov. Kalimantan Barat","kode_wilayah_induk_provinsi":"130000  ","bentuk_pendidikan":"KB","status_sekolah":"Swasta","sinkron_terakhir":"25 Mar 2024 22:08:56","sekolah_id_enkrip":"A4FC32E6AEF57F9F1A02                                                                                "},{"nama":"KB PAUD CAHAYA BANGSA","sekolah_id":"80F52D36-2EE7-4347-A3DC-602586FB5DBA","npsn":69987429,"jumlah_kirim":0,"ptk":1,"pegawai":1,"pd":0,"rombel":0,"jml_rk":0,"jml_lab":0,"jml_perpus":0,"induk_kecamatan":"Kec. Tujuh Belas","kode_wilayah_induk_kecamatan":"130817  ","induk_kabupaten":"Kab. Bengkayang","kode_wilayah_induk_kabupaten":"130800  ","induk_provinsi":"Prov. Kalimantan Barat","kode_wilayah_induk_provinsi":"130000  ","bentuk_pendidikan":"KB","status_sekolah":"Swasta","sinkron_terakhir":"12 Feb 2024 17:08:47","sekolah_id_enkrip":"C7888C01CAE11D09C3FF                                                                                "},{"nama":"PAUD SUMBER ILMU","sekolah_id":"87989999-EE1D-4195-8F48-72724408A9B7","npsn":69943620,"jumlah_kirim":0,"ptk":2,"pegawai":1,"pd":0,"rombel":0,"jml_rk":0,"jml_lab":0,"jml_perpus":0,"induk_kecamatan":"Kec. Tujuh Belas","kode_wilayah_induk_kecamatan":"130817  ","induk_kabupaten":"Kab. Bengkayang","kode_wilayah_induk_kabupaten":"130800  ","induk_provinsi":"Prov. Kalimantan Barat","kode_wilayah_induk_provinsi":"130000  ","bentuk_pendidikan":"KB","status_sekolah":"Swasta","sinkron_terakhir":"13 Feb 2024 14:16:02","sekolah_id_enkrip":"5D2372DC7E0737E7591D                                                                                "},{"nama":"SD NEGERI 01 SEGONDE","sekolah_id":"00AA3D09-30F5-E011-AFCC-DF25DF8160D6","npsn":30103996,"jumlah_kirim":0,"ptk":8,"pegawai":1,"pd":0,"rombel":0,"jml_rk":0,"jml_lab":0,"jml_perpus":0,"induk_kecamatan":"Kec. Tujuh Belas","kode_wilayah_induk_kecamatan":"130817  ","induk_kabupaten":"Kab. Bengkayang","kode_wilayah_induk_kabupaten":"130800  ","induk_provinsi":"Prov. Kalimantan Barat","kode_wilayah_induk_provinsi":"130000  ","bentuk_pendidikan":"SD","status_sekolah":"Negeri","sinkron_terakhir":"24 Jun 2024 10:24:43","sekolah_id_enkrip":"235BFF0F2232170ACB58                                                                                "},{"nama":"SD NEGERI 02 SEGIRING","sekolah_id":"40B73D09-30F5-E011-BDB0-AD88D317689B","npsn":30103977,"jumlah_kirim":4,"ptk":10,"pegawai":2,"pd":75,"rombel":6,"jml_rk":6,"jml_lab":1,"jml_perpus":1,"induk_kecamatan":"Kec. Tujuh Belas","kode_wilayah_induk_kecamatan":"130817  ","induk_kabupaten":"Kab. Bengkayang","kode_wilayah_induk_kabupaten":"130800  ","induk_provinsi":"Prov. Kalimantan Barat","kode_wilayah_induk_provinsi":"130000  ","bentuk_pendidikan":"SD","status_sekolah":"Negeri","sinkron_terakhir":"01 Jun 2024 17:44:23","sekolah_id_enkrip":"E3C849F5F1BBFD206587                                                                                "},{"nama":"SD NEGERI 03 DAWAR","sekolah_id":"50C43D09-30F5-E011-A306-CB2B7E308465","npsn":30104166,"jumlah_kirim":3,"ptk":6,"pegawai":2,"pd":135,"rombel":5,"jml_rk":6,"jml_lab":0,"jml_perpus":1,"induk_kecamatan":"Kec. Tujuh Belas","kode_wilayah_induk_kecamatan":"130817  ","induk_kabupaten":"Kab. Bengkayang","kode_wilayah_induk_kabupaten":"130800  ","induk_provinsi":"Prov. Kalimantan Barat","kode_wilayah_induk_provinsi":"130000  ","bentuk_pendidikan":"SD","status_sekolah":"Negeri","sinkron_terakhir":"05 May 2024 21:36:19","sekolah_id_enkrip":"2A272436A2A401E1DACC                                                                                "},{"nama":"SD NEGERI 04 TAUM","sekolah_id":"60D13D09-30F5-E011-B694-2551B84AF072","npsn":30103985,"jumlah_kirim":0,"ptk":8,"pegawai":2,"pd":0,"rombel":0,"jml_rk":0,"jml_lab":0,"jml_perpus":0,"induk_kecamatan":"Kec. Tujuh Belas","kode_wilayah_induk_kecamatan":"130817  ","induk_kabupaten":"Kab. Bengkayang","kode_wilayah_induk_kabupaten":"130800  ","induk_provinsi":"Prov. Kalimantan Barat","kode_wilayah_induk_provinsi":"130000  ","bentuk_pendidikan":"SD","status_sekolah":"Negeri","sinkron_terakhir":"18 Jun 2024 12:59:07","sekolah_id_enkrip":"4F221B8187BF77DEAA50                                                                                "},{"nama":"SD NEGERI 05 TAUM","sekolah_id":"40DE3D09-30F5-E011-83DF-F1F40E3EC4DF","npsn":30104016,"jumlah_kirim":0,"ptk":17,"pegawai":2,"pd":0,"rombel":0,"jml_rk":0,"jml_lab":0,"jml_perpus":0,"induk_kecamatan":"Kec. Tujuh Belas","kode_wilayah_induk_kecamatan":"130817  ","induk_kabupaten":"Kab. Bengkayang","kode_wilayah_induk_kabupaten":"130800  ","induk_provinsi":"Prov. Kalimantan Barat","kode_wilayah_induk_provinsi":"130000  ","bentuk_pendidikan":"SD","status_sekolah":"Negeri","sinkron_terakhir":"21 Jun 2024 10:17:05","sekolah_id_enkrip":"FAFBFEDE0F1224E6619F                                                                                "},{"nama":"SD NEGERI 06 TAUM","sekolah_id":"40EB3D09-30F5-E011-BCF4-8792D60936C0","npsn":30104005,"jumlah_kirim":0,"ptk":8,"pegawai":1,"pd":0,"rombel":0,"jml_rk":0,"jml_lab":0,"jml_perpus":0,"induk_kecamatan":"Kec. Tujuh Belas","kode_wilayah_induk_kecamatan":"130817  ","induk_kabupaten":"Kab. Bengkayang","kode_wilayah_induk_kabupaten":"130800  ","induk_provinsi":"Prov. Kalimantan Barat","kode_wilayah_induk_provinsi":"130000  ","bentuk_pendidikan":"SD","status_sekolah":"Negeri","sinkron_terakhir":"27 Jun 2024 15:18:34","sekolah_id_enkrip":"2F74D28C226641B4907D                                                                                "},{"nama":"SD NEGERI 07 SEMAWING","sekolah_id":"90F83D09-30F5-E011-B3A9-21A4F3AAC297","npsn":30104188,"jumlah_kirim":2,"ptk":7,"pegawai":2,"pd":42,"rombel":6,"jml_rk":6,"jml_lab":0,"jml_perpus":1,"induk_kecamatan":"Kec. Tujuh Belas","kode_wilayah_induk_kecamatan":"130817  ","induk_kabupaten":"Kab. Bengkayang","kode_wilayah_induk_kabupaten":"130800  ","induk_provinsi":"Prov. Kalimantan Barat","kode_wilayah_induk_provinsi":"130000  ","bentuk_pendidikan":"SD","status_sekolah":"Negeri","sinkron_terakhir":"29 Jun 2024 01:02:46","sekolah_id_enkrip":"C2600609D35362C85180                                                                                "},{"nama":"SD NEGERI 08 SEMAWING","sekolah_id":"B0053E09-30F5-E011-B325-ED8E8EF1CCB9","npsn":30103960,"jumlah_kirim":6,"ptk":12,"pegawai":3,"pd":215,"rombel":9,"jml_rk":11,"jml_lab":0,"jml_perpus":1,"induk_kecamatan":"Kec. Tujuh Belas","kode_wilayah_induk_kecamatan":"130817  ","induk_kabupaten":"Kab. Bengkayang","kode_wilayah_induk_kabupaten":"130800  ","induk_provinsi":"Prov. Kalimantan Barat","kode_wilayah_induk_provinsi":"130000  ","bentuk_pendidikan":"SD","status_sekolah":"Negeri","sinkron_terakhir":"12 Jun 2024 09:45:35","sekolah_id_enkrip":"6978305073415599F50E                                                                                "},{"nama":"SD NEGERI 09 SEMAWING","sekolah_id":"D0123E09-30F5-E011-9FEB-350C73A2E264","npsn":30103949,"jumlah_kirim":0,"ptk":11,"pegawai":1,"pd":0,"rombel":0,"jml_rk":0,"jml_lab":0,"jml_perpus":0,"induk_kecamatan":"Kec. Tujuh Belas","kode_wilayah_induk_kecamatan":"130817  ","induk_kabupaten":"Kab. Bengkayang","kode_wilayah_induk_kabupaten":"130800  ","induk_provinsi":"Prov. Kalimantan Barat","kode_wilayah_induk_provinsi":"130000  ","bentuk_pendidikan":"SD","status_sekolah":"Negeri","sinkron_terakhir":"27 Jun 2024 15:00:02","sekolah_id_enkrip":"4DCCC05C55A364573ACF                                                                                "},{"nama":"SD NEGERI 10 LAEK","sekolah_id":"C01F3E09-30F5-E011-999C-E5F0936482C2","npsn":30103953,"jumlah_kirim":0,"ptk":9,"pegawai":2,"pd":0,"rombel":0,"jml_rk":0,"jml_lab":0,"jml_perpus":0,"induk_kecamatan":"Kec. Tujuh Belas","kode_wilayah_induk_kecamatan":"130817  ","induk_kabupaten":"Kab. Bengkayang","kode_wilayah_induk_kabupaten":"130800  ","induk_provinsi":"Prov. Kalimantan Barat","kode_wilayah_induk_provinsi":"130000  ","bentuk_pendidikan":"SD","status_sekolah":"Negeri","sinkron_terakhir":"21 Jun 2024 07:39:51","sekolah_id_enkrip":"49A40F5C49A2F57A0F30                                                                                "},{"nama":"SMP NEGERI 1 TUJUH BELAS","sekolah_id":"4076B709-30F5-E011-B496-D1F86FD41F1D","npsn":30104045,"jumlah_kirim":14,"ptk":16,"pegawai":4,"pd":227,"rombel":8,"jml_rk":11,"jml_lab":1,"jml_perpus":1,"induk_kecamatan":"Kec. Tujuh Belas","kode_wilayah_induk_kecamatan":"130817  ","induk_kabupaten":"Kab. Bengkayang","kode_wilayah_induk_kabupaten":"130800  ","induk_provinsi":"Prov. Kalimantan Barat","kode_wilayah_induk_provinsi":"130000  ","bentuk_pendidikan":"SMP","status_sekolah":"Negeri","sinkron_terakhir":"25 Jun 2024 08:41:15","sekolah_id_enkrip":"911FCE52C2A874D040FE                                                                                "},{"nama":"SMP NEGERI 2 TUJUH BELAS","sekolah_id":"20C5B8E1-ECF7-E111-B335-FD8F646359A3","npsn":30108321,"jumlah_kirim":4,"ptk":10,"pegawai":4,"pd":60,"rombel":3,"jml_rk":5,"jml_lab":2,"jml_perpus":1,"induk_kecamatan":"Kec. Tujuh Belas","kode_wilayah_induk_kecamatan":"130817  ","induk_kabupaten":"Kab. Bengkayang","kode_wilayah_induk_kabupaten":"130800  ","induk_provinsi":"Prov. Kalimantan Barat","kode_wilayah_induk_provinsi":"130000  ","bentuk_pendidikan":"SMP","status_sekolah":"Negeri","sinkron_terakhir":"21 Jun 2024 21:01:29","sekolah_id_enkrip":"952DEABFBBCDB172ED5E                                                                                "},{"nama":"SMP NEGERI 3 TUJUH BELAS","sekolah_id":"76E4ADDD-46E4-4483-90B2-7EEEBC02C1E2","npsn":69775479,"jumlah_kirim":6,"ptk":11,"pegawai":2,"pd":120,"rombel":6,"jml_rk":6,"jml_lab":1,"jml_perpus":4,"induk_kecamatan":"Kec. Tujuh Belas","kode_wilayah_induk_kecamatan":"130817  ","induk_kabupaten":"Kab. Bengkayang","kode_wilayah_induk_kabupaten":"130800  ","induk_provinsi":"Prov. Kalimantan Barat","kode_wilayah_induk_provinsi":"130000  ","bentuk_pendidikan":"SMP","status_sekolah":"Negeri","sinkron_terakhir":"23 Jun 2024 18:18:17","sekolah_id_enkrip":"14187223CF3CA2FE169B                                                                                "},{"nama":"SMAN 1 TUJUH BELAS","sekolah_id":"00C2DA00-ED6B-4766-9904-369AED942439","npsn":69831558,"jumlah_kirim":0,"ptk":15,"pegawai":2,"pd":0,"rombel":0,"jml_rk":0,"jml_lab":0,"jml_perpus":0,"induk_kecamatan":"Kec. Tujuh Belas","kode_wilayah_induk_kecamatan":"130817  ","induk_kabupaten":"Kab. Bengkayang","kode_wilayah_induk_kabupaten":"130800  ","induk_provinsi":"Prov. Kalimantan Barat","kode_wilayah_induk_provinsi":"130000  ","bentuk_pendidikan":"SMA","status_sekolah":"Negeri","sinkron_terakhir":"08 Jun 2024 15:45:19","sekolah_id_enkrip":"FBC8D9AC1DCF6E977905                                                                                "}]